causal_curve/__init__.py
causal_curve/core.py
causal_curve/gps_classifier.py
causal_curve/gps_core.py
causal_curve/gps_regressor.py
causal_curve/mediation.py
causal_curve/tmle_core.py
causal_curve/tmle_regressor.py
causal_curve-1.0.6.dist-info/LICENSE
causal_curve-1.0.6.dist-info/METADATA
causal_curve-1.0.6.dist-info/WHEEL
causal_curve-1.0.6.dist-info/top_level.txt
causal_curve-1.0.6.dist-info/RECORD
