Metadata-Version: 2.1
Name: causal-curve
Version: 1.0.6
Summary: A python library with tools to perform causal inference using         observational data when the treatment of interest is continuous.
Home-page: https://github.com/ronikobrosly/causal-curve
Author: Roni Kobrosly
Author-email: roni.kobrosly@gmail.com
License: UNKNOWN
Platform: UNKNOWN
Classifier: Programming Language :: Python :: 3
Classifier: License :: OSI Approved :: MIT License
Classifier: Operating System :: OS Independent
Requires-Python: >=3.6
Requires-Dist: black
Requires-Dist: coverage
Requires-Dist: future
Requires-Dist: joblib
Requires-Dist: numpy
Requires-Dist: numpydoc
Requires-Dist: pandas
Requires-Dist: patsy
Requires-Dist: progressbar2
Requires-Dist: pygam
Requires-Dist: pytest
Requires-Dist: python-dateutil
Requires-Dist: python-utils
Requires-Dist: pytz
Requires-Dist: scikit-learn
Requires-Dist: scipy
Requires-Dist: six
Requires-Dist: sphinx-rtd-theme
Requires-Dist: statsmodels
